LICENSE.md
MANIFEST.in
README.md
pyproject.toml
setup.py
association_measures/__init__.py
association_measures/binomial.c
association_measures/binomial.pyx
association_measures/comparisons.py
association_measures/frequencies.py
association_measures/grids.py
association_measures/measures.py
association_measures/version.py
association_measures.egg-info/PKG-INFO
association_measures.egg-info/SOURCES.txt
association_measures.egg-info/dependency_links.txt
association_measures.egg-info/requires.txt
association_measures.egg-info/top_level.txt
tests/test_binomial.py
tests/test_frequencies.py
tests/test_grids.py
tests/test_measures.py
tests/test_nas.py
tests/test_readme.py
venv/lib64/python3.10/site-packages/Cython/Runtime/refnanny.pyx
venv/lib64/python3.10/site-packages/Cython/Utility/CConvert.pyx
venv/lib64/python3.10/site-packages/Cython/Utility/CpdefEnums.pyx
venv/lib64/python3.10/site-packages/Cython/Utility/CppConvert.pyx
venv/lib64/python3.10/site-packages/Cython/Utility/MemoryView.pyx
venv/lib64/python3.10/site-packages/Cython/Utility/TestCyUtilityLoader.pyx
venv/lib64/python3.10/site-packages/Cython/Utility/TestCythonScope.pyx
venv/lib64/python3.10/site-packages/Cython/Utility/UFuncs.pyx
venv/lib64/python3.10/site-packages/numpy/_core/tests/examples/cython/checks.pyx
venv/lib64/python3.10/site-packages/numpy/_core/tests/examples/limited_api/limited_api2.pyx
venv/lib64/python3.10/site-packages/numpy/random/_examples/cython/extending.pyx
venv/lib64/python3.10/site-packages/numpy/random/_examples/cython/extending_distributions.pyx
venv/lib64/python3.10/site-packages/scipy/linalg/cython_blas.pyx
venv/lib64/python3.10/site-packages/scipy/linalg/cython_lapack.pyx
venv/lib64/python3.10/site-packages/scipy/linalg/tests/_cython_examples/extending.pyx
venv/lib64/python3.10/site-packages/scipy/optimize/tests/_cython_examples/extending.pyx
venv/lib64/python3.10/site-packages/scipy/special/_ufuncs.pyx
venv/lib64/python3.10/site-packages/scipy/special/_ufuncs_cxx.pyx
venv/lib64/python3.10/site-packages/scipy/special/tests/_cython_examples/extending.pyx