Metadata-Version: 2.2
Name: association-measures
Version: 0.3.1
Summary: Statistical association measures for Python pandas
Home-page: https://github.com/fau-klue/pandas-association-measures
Author: Philipp Heinrich & Markus Opolka
Author-email: philipp.heinrich@fau.de
License: MIT
Classifier: License :: OSI Approved :: MIT License
Classifier: Programming Language :: Python
Classifier: Programming Language :: Python :: 3
Classifier: Programming Language :: Python :: 3.9
Classifier: Programming Language :: Python :: 3.10
Classifier: Programming Language :: Python :: 3.11
Classifier: Programming Language :: Python :: 3.12
Classifier: Programming Language :: Python :: 3.13
Classifier: Programming Language :: Cython
Requires-Python: >=3.9
License-File: LICENSE.md
Requires-Dist: wheel
Requires-Dist: pandas<3.0,>=2.2.2
Requires-Dist: numpy<3.0,>=2.0
Requires-Dist: scipy<2.0,>=1.13.0
Dynamic: author
Dynamic: author-email
Dynamic: classifier
Dynamic: description
Dynamic: description-content-type
Dynamic: home-page
Dynamic: license
Dynamic: requires-dist
Dynamic: requires-python
Dynamic: summary
